<?xml version="1.0" encoding="UTF-8"?>
<Items>
    <item>
        <surname>Schnitzler</surname>
        <forename>Arthur</forename>
        <ID>2121</ID>
        <birth_date>1862-05-15</birth_date>
        <death_date>1931-10-21</death_date>
        <start_date_written>15.05.1862</start_date_written>
        <end_date_written>21.10.1931</end_date_written>
        <profession>90.0</profession>
        <gender>male</gender>
    </item>
    <item>
        <surname>Schnitzler</surname>
        <forename>Arthur</forename>
        <ID>2121</ID>
        <birth_date>1862-05-15</birth_date>
        <death_date>1931-10-21</death_date>
        <start_date_written>15.05.1862</start_date_written>
        <end_date_written>21.10.1931</end_date_written>
        <profession>97.0</profession>
        <gender>male</gender>
    </item>
    <item>
        <surname>Machar</surname>
        <forename>Josef Svatopluk</forename>
        <ID>2124</ID>
        <birth_date>1864-02-29</birth_date>
        <death_date>1942-03-17</death_date>
        <start_date_written>29.02.1864</start_date_written>
        <end_date_written>17.03.1942</end_date_written>
        <profession>90.0</profession>
        <gender>male</gender>
    </item>
    <item>
        <surname>Plessner</surname>
        <forename>Elsa</forename>
        <ID>2128</ID>
        <birth_date>1875-08-22</birth_date>
        <death_date>1932-05-01</death_date>
        <start_date_written>22.08.1875</start_date_written>
        <end_date_written>01.05.1932</end_date_written>
        <profession>91.0</profession>
        <gender>female</gender>
    </item>
    <item>
        <surname>Bahr</surname>
        <forename>Alois</forename>
        <ID>2132</ID>
        <birth_date>1834-04-11</birth_date>
        <death_date>1898-09-05</death_date>
        <start_date_written>11.04.1834</start_date_written>
        <end_date_written>05.09.1898</end_date_written>
        <profession>94.0</profession>
        <gender>male</gender>
    </item>
    <item>
        <surname>Bahr</surname>
        <forename>Alois</forename>
        <ID>2132</ID>
        <birth_date>1834-04-11</birth_date>
        <death_date>1898-09-05</death_date>
        <start_date_written>11.04.1834</start_date_written>
        <end_date_written>05.09.1898</end_date_written>
        <profession>95.0</profession>
        <gender>male</gender>
    </item>
    <item>
        <surname>Popper-Lynkeus</surname>
        <forename>Josef</forename>
        <ID>2135</ID>
        <birth_date>1838-02-21</birth_date>
        <death_date>1921-12-22</death_date>
        <start_date_written>21.02.1838</start_date_written>
        <end_date_written>22.12.1921</end_date_written>
        <profession>90.0</profession>
        <gender>male</gender>
    </item>
    <item>
        <surname>Schönlein</surname>
        <forename>Johann Lukas</forename>
        <ID>2138</ID>
        <birth_date>1793-11-30</birth_date>
        <death_date>1864-01-23</death_date>
        <start_date_written>30.11.1793</start_date_written>
        <end_date_written>23.01.1864</end_date_written>
        <profession>97.0</profession>
        <gender>male</gender>
    </item>
    <item>
        <surname>D’Annunzio</surname>
        <forename>Gabriele</forename>
        <ID>2142</ID>
        <birth_date>1863-03-12</birth_date>
        <death_date>1938-03-01</death_date>
        <start_date_written>12.03.1863</start_date_written>
        <end_date_written>01.03.1938</end_date_written>
        <profession>90.0</profession>
        <gender>male</gender>
    </item>
    <item>
        <surname>Altenberg</surname>
        <forename>Peter</forename>
        <ID>2147</ID>
        <birth_date>1859-03-09</birth_date>
        <death_date>1919-01-08</death_date>
        <start_date_written>09.03.1859</start_date_written>
        <end_date_written>08.01.1919</end_date_written>
        <profession>90.0</profession>
        <gender>male</gender>
    </item>
    <item>
        <surname>Bauer</surname>
        <forename>Julius</forename>
        <ID>2150</ID>
        <birth_date>1853-10-15</birth_date>
        <death_date>1941-06-11</death_date>
        <start_date_written>15.10.1853</start_date_written>
        <end_date_written>11.06.1941</end_date_written>
        <profession>90.0</profession>
        <gender>male</gender>
    </item>
    <item>
        <surname>Bauer</surname>
        <forename>Julius</forename>
        <ID>2150</ID>
        <birth_date>1853-10-15</birth_date>
        <death_date>1941-06-11</death_date>
        <start_date_written>15.10.1853</start_date_written>
        <end_date_written>11.06.1941</end_date_written>
        <profession>99.0</profession>
        <gender>male</gender>
    </item>
    <item>
        <surname>Bauer</surname>
        <forename>Julius</forename>
        <ID>2150</ID>
        <birth_date>1853-10-15</birth_date>
        <death_date>1941-06-11</death_date>
        <start_date_written>15.10.1853</start_date_written>
        <end_date_written>11.06.1941</end_date_written>
        <profession>100.0</profession>
        <gender>male</gender>
    </item>
    <item>
        <surname>Chiavacci</surname>
        <forename>Vincenz</forename>
        <ID>2154</ID>
        <birth_date>1847-06-15</birth_date>
        <death_date>1916-02-02</death_date>
        <start_date_written>15.06.1847</start_date_written>
        <end_date_written>02.02.1916</end_date_written>
        <profession>90.0</profession>
        <gender>male</gender>
    </item>
    <item>
        <surname>Chiavacci</surname>
        <forename>Vincenz</forename>
        <ID>2154</ID>
        <birth_date>1847-06-15</birth_date>
        <death_date>1916-02-02</death_date>
        <start_date_written>15.06.1847</start_date_written>
        <end_date_written>02.02.1916</end_date_written>
        <profession>99.0</profession>
        <gender>male</gender>
    </item>
   
</Items>
